[
    {
        "title": "NIS2 compliance: The Kafkaesque burden on Europe’s companies",
        "url": "https://broomstick.tymyrddin.dev/posts/kafkaesque-nis2/",
        "date": "2025-11-26"
    },
    {
        "title": "How a rebellion became a bureaucracy",
        "url": "https://broomstick.tymyrddin.dev/posts/rebellion/",
        "date": "2026-06-04"
    },
    {
        "title": "What institutions do to successful ideas",
        "url": "https://broomstick.tymyrddin.dev/posts/institutionalisation/",
        "date": "2026-06-04"
    }
]
